adg/__init__.py
adg/bimsrg.py
adg/bmbpt.py
adg/diag.py
adg/main.py
adg/mbpt.py
adg/pbmbpt.py
adg/run.py
adg/tools.py
adg/tsd.py
adg-3.1.0.data/data/share/doc/adg/README.md
adg-3.1.0.data/data/share/man/man1/adg.1
adg-3.1.0.dist-info/LICENSE.txt
adg-3.1.0.dist-info/METADATA
adg-3.1.0.dist-info/WHEEL
adg-3.1.0.dist-info/entry_points.txt
adg-3.1.0.dist-info/top_level.txt
adg-3.1.0.dist-info/RECORD
